copick_torch/__init__.py
copick_torch/augmentations.py
copick_torch/cli.py
copick_torch/copick.py
copick_torch/dataset.py
copick_torch/logging.py
copick_torch/minimal_dataset.py
copick_torch/parallelization.py
copick_torch/samplers.py
copick_torch/entry_points/__init__.py
copick_torch/entry_points/run_downsample.py
copick_torch/entry_points/run_membrane_seg.py
copick_torch/entry_points/utils.py
copick_torch/filters/__init__.py
copick_torch/filters/downsample.py
copick_torch/inference/__init__.py
copick_torch/inference/membrain_seg.py
copick_torch-1.0.1.dist-info/METADATA
copick_torch-1.0.1.dist-info/WHEEL
copick_torch-1.0.1.dist-info/entry_points.txt
copick_torch-1.0.1.dist-info/licenses/LICENSE
copick_torch-1.0.1.dist-info/RECORD
