Metadata-Version: 2.4
Name: copick-torch
Version: 1.0.1
Summary: Torch utilities for copick
Project-URL: Repository, https://github.com/copick/copick-torch
Project-URL: Issues, https://github.com/copick/copick-torch/issues
Project-URL: Documentation, https://github.com/copick/copick-torch#README.md
Project-URL: Bug Tracker, https://github.com/copick/copick-torch/issues
Project-URL: Source Code, https://github.com/copick/copick-torch
Project-URL: User Support, https://github.com/copick/copick-torch/issues
Author-email: Kyle Harrington <czi@kyleharrington.com>, Jonathan Schwartz <jonathan.schwartz@czii.org>
License: MIT License
License-File: LICENSE
Keywords: annotation,copick,cryo-et,cryoet,pytorch,tomography,torch
Classifier: Development Status :: 2 - Pre-Alpha
Classifier: Intended Audience :: Developers
Classifier: License :: OSI Approved :: MIT License
Classifier: Operating System :: OS Independent
Classifier: Programming Language :: Python
Classifier: Programming Language :: Python :: 3
Classifier: Programming Language :: Python :: 3 :: Only
Classifier: Programming Language :: Python :: 3.9
Classifier: Programming Language :: Python :: 3.10
Classifier: Programming Language :: Python :: 3.11
Classifier: Programming Language :: Python :: 3.12
Classifier: Programming Language :: Python :: 3.13
Classifier: Programming Language :: Python :: Implementation :: CPython
Classifier: Programming Language :: Python :: Implementation :: PyPy
Classifier: Topic :: Scientific/Engineering :: Image Processing
Requires-Python: >=3.9
Requires-Dist: copick-utils
Requires-Dist: copick>=1.8.2
Requires-Dist: dask
Requires-Dist: einops
Requires-Dist: gdown
Requires-Dist: matplotlib
Requires-Dist: membrain-seg
Requires-Dist: monai
Requires-Dist: mrcfile
Requires-Dist: numcodecs<0.16.0
Requires-Dist: numpy
Requires-Dist: pandas>=2.2.3
Requires-Dist: pyarrow>=19.0.1
Requires-Dist: pytest>=8.3.5
Requires-Dist: scikit-image
Requires-Dist: scikit-learn>=1.6.1
Requires-Dist: scipy
Requires-Dist: torch
Requires-Dist: torchvision>=0.21.0
Requires-Dist: zarr
Provides-Extra: dev
Requires-Dist: black>=25.1.0; extra == 'dev'
Requires-Dist: hatch-vcs>=0.4.0; extra == 'dev'
Requires-Dist: hatchling>=1.25.0; extra == 'dev'
Requires-Dist: ipykernel>=6.29.5; extra == 'dev'
Requires-Dist: jupyter>=1.1.1; extra == 'dev'
Requires-Dist: pre-commit>=4.2.0; extra == 'dev'
Requires-Dist: ruff>=0.12.0; extra == 'dev'
Provides-Extra: test
Requires-Dist: pytest; extra == 'test'
Requires-Dist: pytest-cov; extra == 'test'
Requires-Dist: tox; extra == 'test'
Requires-Dist: tox-gh-actions; extra == 'test'
Requires-Dist: tox-uv; extra == 'test'
